{"cons": {u"mile": 1, u"love": 2, u"although": 1, u"office": 2, u"house": 1, u"ani": 2, u"fellow": 1, u"patience": 2, u"\u2013": 3, u"paper": 1, u"patience.hours": 1, u"traveling": 1, u"hours.": 1, u"job.": 1, u"state.": 1, u"sake.": 1, u"!": 1, u"increase": 1, u""ll": 1, u"would": 1, u",": 6, u".": 3, u"either.": 1, u"tutor": 1, u"contact": 2, u"board": 1, u"face-to-face": 1, u":": 2, u""s": 1, u"away.": 1, u"company": 1, u"however": 1, u"hurt": 1, u"part": 1, u"student": 3, u"mandate": 1, u"teach": 1, u"kid": 1, u"school": 1, u"enrollment": 1, u"work": 1, u"n"t": 1, u"year-by-year": 1, u"thi": 1, u"time": 1, u"z": 1, u"con": 3}, "pros": {u"mile": 1, u"love": 2, u"although": 1, u"office": 2, u"house": 1, u"ani": 2, u"fellow": 1, u"patience": 2, u"\u2013": 3, u"paper": 1, u"patience.hours": 1, u"traveling": 1, u"hours.": 1, u"job.": 1, u"state.": 1, u"sake.": 1, u"!": 1, u"increase": 1, u""ll": 1, u"would": 1, u",": 6, u".": 3, u"either.": 1, u"tutor": 1, u"contact": 2, u"board": 1, u"face-to-face": 1, u":": 2, u""s": 1, u"away.": 1, u"company": 1, u"however": 1, u"hurt": 1, u"part": 1, u"student": 3, u"mandate": 1, u"teach": 1, u"kid": 1, u"school": 1, u"enrollment": 1, u"work": 1, u"n"t": 1, u"year-by-year": 1, u"thi": 1, u"time": 1, u"z": 1, u"con": 3}}