{"cons": {u"hierarchal": 1, u""s": 1, u"like": 1, u"internship": 1, u"(": 1, u"-": 2, u"benefit": 1, u"except": 1, u")": 1, u"\u2013": 1, u"days-": 1, u"vacation": 1, u"somewhat": 1, u"stereo-typical": 1, u"kitchen": 1, u"low-pay": 1, u",": 1, u"temperamental": 1, u"con": 1}, "pros": {u"hierarchal": 1, u""s": 1, u"like": 1, u"internship": 1, u"(": 1, u"-": 2, u"benefit": 1, u"except": 1, u")": 1, u"\u2013": 1, u"days-": 1, u"vacation": 1, u"somewhat": 1, u"stereo-typical": 1, u"kitchen": 1, u"low-pay": 1, u",": 1, u"temperamental": 1, u"con": 1}}