{"cons": {u"headache": 1, u"ever.": 1, u"love": 1, u"monotonous": 1, u"happy.": 1, u"money": 1, u"dure": 1, u"one": 1, u"\u2013": 2, u"computer": 1, u"long": 1, u"year": 1, u""s": 1, u"skill": 1, u".": 2, u"coo.": 1, u"really": 1, u"hit": 1, u"lie": 1, u"management": 1, u"develop": 1, u"goal": 1, u"would": 2, u"turn": 1, u"migraine": 1, u"pay": 1, u"avoid": 1, u"constantly": 2, u",": 4, u"per": 1, u"eat": 1, u"also": 2, u"time.": 1, u"without": 1, u"take": 1, u""ve": 1, u"new": 1, u""ll": 1, u"brisk": 1, u"sedentary.": 1, u"difficult": 1, "good": 1, u"star": 1, u"raise": 1, "get": 3, u"company": 2, u"time": 1, u"stop": 1, u"employees.": 1, u"lunch": 2, u"afraid": 1, u"plan": 1, u"never": 1, u"8": 1, u"everyone": 1, u"trouble": 1, u"walk": 1, u"sneeze": 1, u"day": 2, u"care": 1, u"terrible": 1, u"dictatorship": 1, u"hour": 1, u"oh": 1, u"amount": 1, u"could": 1, u"work": 1, u"well": 1, u"list": 1, u"us": 1, u"tell": 1, u"n"t": 2, u"rather": 1, u"severe": 1, u""re": 2, u"place": 1, u"here.": 1, u"thi": 1, u"learn": 1, u"position": 2, u"typical": 1, u"make": 2, u"con": 3}, "pros": {u"headache": 1, u"ever.": 1, u"love": 1, u"monotonous": 1, u"happy.": 1, u"money": 1, u"dure": 1, u"one": 1, u"\u2013": 2, u"computer": 1, u"long": 1, u"year": 1, u""s": 1, u"skill": 1, u".": 2, u"coo.": 1, u"really": 1, u"hit": 1, u"lie": 1, u"management": 1, u"develop": 1, u"goal": 1, u"would": 2, u"turn": 1, u"migraine": 1, u"pay": 1, u"avoid": 1, u"constantly": 2, u",": 4, u"per": 1, u"eat": 1, u"also": 2, u"time.": 1, u"without": 1, u"take": 1, u""ve": 1, u"new": 1, u""ll": 1, u"brisk": 1, u"sedentary.": 1, u"difficult": 1, "good": 1, u"star": 1, u"raise": 1, "get": 3, u"company": 2, u"time": 1, u"stop": 1, u"employees.": 1, u"lunch": 2, u"afraid": 1, u"plan": 1, u"never": 1, u"8": 1, u"everyone": 1, u"trouble": 1, u"walk": 1, u"sneeze": 1, u"day": 2, u"care": 1, u"terrible": 1, u"dictatorship": 1, u"hour": 1, u"oh": 1, u"amount": 1, u"could": 1, u"work": 1, u"well": 1, u"list": 1, u"us": 1, u"tell": 1, u"n"t": 2, u"rather": 1, u"severe": 1, u""re": 2, u"place": 1, u"here.": 1, u"thi": 1, u"learn": 1, u"position": 2, u"typical": 1, u"make": 2, u"con": 3}}