{"cons": {u"alot": 1, u"management": 1, u"money": 1, u"look": 1, u"hour": 1, u"always": 3, u"company": 1, u"back": 1, u"business": 1, u"\u2013": 2, u"cut": 2, u"pay.": 1, u"take": 1, u"way": 3, "lose": 1, u"put": 1, u"home": 1, u"find": 2, u"con": 2}, "pros": {u"alot": 1, u"management": 1, u"money": 1, u"look": 1, u"hour": 1, u"always": 3, u"company": 1, u"back": 1, u"business": 1, u"\u2013": 2, u"cut": 2, u"pay.": 1, u"take": 1, u"way": 3, "lose": 1, u"put": 1, u"home": 1, u"find": 2, u"con": 2}}