<name>George I. Sanchez Charter HS Reviews </name>
<url>http://www.glassdoor.com/Reviews/George-I-Sanchez-Charter-HS-Reviews-E271158.htm
</url>
<reviews>
<review>
<date>2013-08-13</date>
<rating>1.0</rating>
<upvote>0</upvote>
<employee-type>Tutor (Current Employee)</employee-type>
<title>

“The Worst Place to Work”

</title><pros>Pros – None there are no pros to working here.</pros>
<cons>Cons – No BenefitsMultiple Duties not related to your job responsibilities</cons>
<advice-to-management>Advice to Senior Management – Check yourself</advice-to-management>
<recommended>No</recommended>
</review>

</reviews>