<name>U.S. Senator Bob Corker Reviews </name>
<url>http://www.glassdoor.com/Reviews/U-S-Senator-Bob-Corker-Reviews-E322754.htm
</url>
<reviews>
<review>
<date>2010-05-25</date>
<rating>4.0</rating>
<upvote>0</upvote>
<employee-type>Intern (Former Employee)</employee-type>
<title>

“Smart man does his homework”

</title><pros>Pros – Sen. Corker knows how to delegate and make informed decisions. Therefore, he relies on his staff to put together well rounded arguments and often plays devil's advocate to try to get to the best solution. The staff are nice and friendly and open.Sen. Corker makes people feel appreciated, seen and heard. He is honest and expects his office to run as such.</pros>
<cons>Cons – Often times it does get "political" when working in an office. There is a sense of heirarchy to some LAs and LCs.</cons>
<advice-to-management>Advice to Senior Management – Keep up the good work.</advice-to-management>
<recommended>Yes</recommended>
</review>

</reviews>