<name>J. Senter Realty Reviews </name>
<url>http://www.glassdoor.com/Reviews/J-Senter-Realty-Reviews-E343575.htm
</url>
<reviews>
<review>
<date>2010-08-30</date>
<rating>3.0</rating>
<upvote>0</upvote>
<employee-type>Agent (Former Employee)</employee-type>
<title>

“Agent working for high end luxury rentals”

</title><pros>Pros – Best reasons to work there were the flexibility to schedule your own hours and to network among owners and clients</pros>
<cons>Cons – Not a large potential for growth, management is not willing to see the opportunities presented for growth in the new market.</cons>
<advice-to-management>Advice to Senior Management – It would be beneficial to consider the growth opportunities for each agent and to assist in helping to encourage growth within the company</advice-to-management>
<recommended></recommended>
</review>

</reviews>