<name>W. Lerman Architecture Reviews </name>
<url>http://www.glassdoor.com/Reviews/W-Lerman-Architecture-Reviews-E384425.htm
</url>
<reviews>
<review>
<date>2011-03-13</date>
<rating>3.0</rating>
<upvote>0</upvote>
<employee-type>Job Captain (Former Employee)</employee-type>
<title>

“Growing Experience”

</title><pros>Pros – Because It's a small firm it allows you to be exposed to all phases of the project and you have the opportunity to have client interaction and consultants too. Office environment is good nice easy good people.</pros>
<cons>Cons – Money in this company is a big issue. You do not get direct deposit and as an advice you should cash checks before making a deposit to  you account.. (They might bounce)....</cons>
<advice-to-management>Advice to Senior Management – There should be more office team meetings to check status of projects.</advice-to-management>
<recommended>No</recommended>
</review>

</reviews>