<name>Audrey D. Shields, Attorney at Law Reviews </name>
<url>http://www.glassdoor.com/Reviews/Audrey-D-Shields-Attorney-at-Law-Reviews-E449005.htm
</url>
<reviews>
<review>
<date>2011-11-17</date>
<rating>5.0</rating>
<upvote>0</upvote>
<employee-type>Paralegal (Former Employee)</employee-type>
<title>

“Great attorney.”

</title><pros>Pros – smart, fun lady to work for.</pros>
<cons>Cons – No health insurance, but check back soon.</cons>
<advice-to-management>Advice to Senior Management – Great place to work.</advice-to-management>
<recommended>Yes</recommended>
</review>

</reviews>