<name>GNITS Reviews </name>
<url>http://www.glassdoor.com/Reviews/GNITS-Reviews-E545586.htm
</url>
<reviews>
<review>
<date>2012-07-05</date>
<rating>4.0</rating>
<upvote>0</upvote>
<employee-type>Graduate Student (Current Employee)</employee-type>
<title>

“its fine..”

</title><pros>Pros – it is a place where i can be myself.</pros>
<cons>Cons – the environment around sometimes very depressing.</cons>
<advice-to-management>Advice to Senior Management – knowledge !</advice-to-management>
<recommended></recommended>
</review>

</reviews>