<name>H Clay Moore Reviews </name>
<url>http://www.glassdoor.com/Reviews/H-Clay-Moore-Reviews-E581897.htm
</url>
<reviews>
<review>
<date>2012-08-07</date>
<rating>3.0</rating>
<upvote>0</upvote>
<employee-type>Inside Sales (Former Employee)</employee-type>
<title>

“Proceed With Caution”

</title><pros>Pros – Good pay, work environment, benefits (paid medical anyway); If you work hard and stay you can make some good money;</pros>
<cons>Cons – Cliquey - if you're not in the clique, you're out; Very political, conservative, good ol boy..</cons>
<advice-to-management>Yes, I would recommend this company to a friend – I'm optimistic about the outlook for this company</advice-to-management>
</review>

</reviews>