<name>I Love Art UK Reviews </name>
<url>http://www.glassdoor.com/Reviews/I-Love-Art-UK-Reviews-E600108.htm
</url>
<reviews>
<review>
<date>2012-08-30</date>
<rating>1.0</rating>
<upvote>0</upvote>
<employee-type>N/A (Former Employee)</employee-type>
<title>

“Not a great experience for internships”

</title><pros>Pros – The ability to network with other individualsThe location is fantastic and culturally excitingThe exposure to the industry in general is usefulThe external contact with other similar organisations</pros>
<cons>Cons – The salary is far below industry standardsThe lack of guidance and training is not consistent with an internshipThe constant office politics are unnecessarily drainingThe company has a very poor and confusing structure</cons>
<advice-to-management>Advice to Senior Management – The company would be better with a more cohesive structure and clear heirarchy</advice-to-management>
<recommended>No</recommended>
</review>

</reviews>