<name>Z House Realty Group Reviews </name>
<url>http://www.glassdoor.com/Reviews/Z-House-Realty-Group-Reviews-E625728.htm
</url>
<reviews>
<review>
<date>2012-10-18</date>
<rating>5.0</rating>
<upvote>0</upvote>
<employee-type>Marketing Assistant (Former Employee)</employee-type>
<title>

“Zhouse Realty employees are as important as their clients”

</title><pros>Pros – Strong teamwork atmosphereProfessional developmentCutting edge technology and training.Family friendly atmosphereBrand new office strategic location</pros>
<cons>Cons – If you need hands on management this is not the place for you.  Self management is the key to the success of this office.</cons>
<advice-to-management>Advice to Senior Management – Stay true to your original business concept because it works!</advice-to-management>
<recommended>Yes</recommended>
</review>

</reviews>