<name>D-TA Systems Reviews </name>
<url>http://www.glassdoor.com/Reviews/D-TA-Systems-Reviews-E666475.htm
</url>
<reviews>
<review>
<date>2013-03-07</date>
<rating>1.0</rating>
<upvote>0</upvote>
<employee-type>Anonymous Employee (Former Employee)</employee-type>
<title>

“This is a  company with no morals”

</title><pros>Pros – Great technology (badly executed).They have some awesomely smart people</pros>
<cons>Cons – After leaving they do not pay bills and use you personal info for company business.Company does not understand how to operate in a US environment and does what it can to circumvent the rules of business in the US.</cons>
<advice-to-management>Advice to Senior Management – Stop doing business in US or get a grip on how to do it.Get your company values in place before you hire any more US people.</advice-to-management>
<recommended>No</recommended>
</review>

</reviews>