<name>F Hinds Reviews </name>
<url>http://www.glassdoor.com/Reviews/F-Hinds-Reviews-E673302.htm
</url>
<reviews>
<review>
<date>2013-03-30</date>
<rating>3.0</rating>
<upvote>0</upvote>
<employee-type>Sales Advisor (Former Employee)</employee-type>
<title>

“Great team”

</title><pros>Pros – Fab group of people, good discount, good training</pros>
<cons>Cons – Un flexible working hours, poor pay, management issues</cons>
<advice-to-management>Yes, I would recommend this company to a friend</advice-to-management>
</review>

</reviews>