<name>G. Cotter Enterprises Reviews </name>
<url>http://www.glassdoor.com/Reviews/G-Cotter-Enterprises-Reviews-E721931.htm
</url>
<reviews>
<review>
<date>2013-09-13</date>
<rating>3.0</rating>
<upvote>0</upvote>
<employee-type>Anonymous Employee (Former Employee)</employee-type>
<title>

“Lots of fun with fellow employees but the potential for growth is very small.”

</title><pros>Pros – 90% of the people you work with are great. Everyone likes to have a good time and will help you out when you need it.  The job is very interesting when you are working on jobs for the Navy.</pros>
<cons>Cons – Projects are not planned well and management is always changing there mind about the priority of jobs so you will stop and start the same job several times.  The pay is not much and you could have to wait a while to get a raise.</cons>
<advice-to-management>Advice to Senior Management – Plan and communicate better is workers.</advice-to-management>
<recommended>No</recommended>
</review>

</reviews>