<name>Bohiyaanam Reviews </name>
<url>http://www.glassdoor.com/Reviews/Bohiyaanam-Reviews-E733120.htm
</url>
<reviews>
<review>
<date>2013-10-12</date>
<rating>3.0</rating>
<upvote>0</upvote>
<employee-type>Anonymous Employee (Former Employee)</employee-type>
<title>

“An Exciting and Learning Experience!!!1”

</title><pros>Pros – There were good opportunities,had some good experiences learnt a lot lot of scope for improving one person.Good for starting a carrer</pros>
<cons>Cons – No professionalism towards a intern,no recreational activites,deadline to work was never justified, some people knew nothing about the job</cons>
<advice-to-management></advice-to-management>
</review>

</reviews>